bitcoin_rpc_client/__init__.py
bitcoin_rpc_client/client_async.py
bitcoin_rpc_client/client_sync.py
bitcoin_rpc_client/error.py
bitcoin_rpc_client-0.1.2.dist-info/LICENSE
bitcoin_rpc_client-0.1.2.dist-info/METADATA
bitcoin_rpc_client-0.1.2.dist-info/WHEEL
bitcoin_rpc_client-0.1.2.dist-info/top_level.txt
bitcoin_rpc_client-0.1.2.dist-info/RECORD
