Metadata-Version: 2.1
Name: bitcoin-rpc-client
Version: 0.1.2
Summary: Bitcoin RPC Client
Home-page: https://github.com/c0mm4nd/bitcoin-rpc-client
Author: CommandM
Author-email: maoxs2@gmail.com
License: MIT
Keywords: bitcoin btc json-rpc rpc client
Platform: UNKNOWN
Classifier: License :: OSI Approved :: MIT License
Classifier: Programming Language :: Python :: 3
Classifier: Programming Language :: Python :: 3.7
Classifier: Programming Language :: Python :: 3.8
Classifier: Programming Language :: Python :: 3.9
Classifier: Programming Language :: Python :: 3.10
Classifier: Programming Language :: Python :: 3 :: Only
Classifier: Topic :: Software Development :: Libraries :: Python Modules
License-File: LICENSE
Requires-Dist: httpx
